starfile/__init__.py
starfile/__main__.py
starfile/functions.py
starfile/parser.py
starfile/typing.py
starfile/utils.py
starfile/writer.py
starfile-0.5.13.dist-info/METADATA
starfile-0.5.13.dist-info/WHEEL
starfile-0.5.13.dist-info/licenses/LICENSE
starfile-0.5.13.dist-info/RECORD
