Metadata-Version: 2.4
Name: starfile
Version: 0.5.13
Summary: STAR file I/O in Python
Project-URL: homepage, https://github.com/teamtomo/starfile
Project-URL: repository, https://github.com/teamtomo/starfile
Author-email: Alister Burt <alisterburt@gmail.com>
License: BSD-3-Clause
License-File: LICENSE
Classifier: Development Status :: 3 - Alpha
Classifier: License :: OSI Approved :: BSD License
Classifier: Programming Language :: Python :: 3
Classifier: Programming Language :: Python :: 3.8
Classifier: Programming Language :: Python :: 3.9
Classifier: Programming Language :: Python :: 3.10
Classifier: Programming Language :: Python :: 3.11
Classifier: Programming Language :: Python :: 3.12
Classifier: Typing :: Typed
Requires-Python: >=3.8
Requires-Dist: numpy
Requires-Dist: pandas>=2.1.1
Requires-Dist: pyarrow
Requires-Dist: typing-extensions
Provides-Extra: dev
Requires-Dist: black; extra == 'dev'
Requires-Dist: ipython; extra == 'dev'
Requires-Dist: mypy; extra == 'dev'
Requires-Dist: pdbpp; extra == 'dev'
Requires-Dist: pre-commit; extra == 'dev'
Requires-Dist: rich; extra == 'dev'
Requires-Dist: ruff; extra == 'dev'
Provides-Extra: test
Requires-Dist: pytest; extra == 'test'
Requires-Dist: pytest-cov; extra == 'test'
